{
  "id": "133",
  "name": "Analyze the sentiment of feedback and send a message on Mattermost",
  "nodes": [
    {
      "name": "Typeform Trigger",
      "type": "n8n-nodes-base.typeformTrigger",
      "position": [
        510,
        260
      ],
      "webhookId": "ad8a87ef-d293-4e48-8d36-838d69ebce0f",
      "parameters": {
        "formId": ""
      },
      "credentials": {
        "typeformApi": "typeform"
      },
      "typeVersion": 1,
      "id": "ca69f480-9e6a-4ba6-810f-fd4ac216c521"
    },
    {
      "name": "Google Cloud Natural Language",
      "type": "n8n-nodes-base.googleCloudNaturalLanguage",
      "position": [
        710,
        260
      ],
      "parameters": {
        "content": "={{$node[\"Typeform Trigger\"].json[\"What did you think about the event?\"]}}",
        "options": {}
      },
      "credentials": {
        "googleCloudNaturalLanguageOAuth2Api": "cloud"
      },
      "typeVersion": 1,
      "id": "7b2d857f-d709-47b2-bf99-33519e8b57be"
    },
    {
      "name": "If Node",
      "type": "n8n-nodes-base.if",
      "position": [
        910,
        260
      ],
      "parameters": {
        "conditions": {
          "number": [
            {
              "value1": "={{$node[\"Google Cloud Natural Language\"].json[\"documentSentiment\"][\"score\"]}}"
            }
          ]
        }
      },
      "typeVersion": 1,
      "id": "a36b7d1d-62b0-4495-b986-f9e30a4e5e31"
    },
    {
      "name": "Mattermost",
      "type": "n8n-nodes-base.mattermost",
      "position": [
        1110,
        160
      ],
      "parameters": {
        "message": "=You got a new feedback with a score of {{$node[\"Google Cloud Natural Language\"].json[\"documentSentiment\"][\"score\"]}}. Here is what it says:{{$node[\"Typeform Trigger\"].json[\"What did you think about the event?\"]}}",
        "channelId": "4h1bz64cyifwxnzojkzh8hxh4a",
        "attachments": [],
        "otherOptions": {}
      },
      "credentials": {
        "mattermostApi": "mattermost"
      },
      "typeVersion": 1,
      "id": "11fc0634-48e7-4f62-b149-ff35e3c3bf24"
    },
    {
      "name": "NoOp",
      "type": "n8n-nodes-base.noOp",
      "position": [
        1110,
        360
      ],
      "parameters": {},
      "typeVersion": 1,
      "id": "60cdf8e4-fd25-4c4a-8b53-ed16b055f40a"
    },
    {
      "id": "documentation-node",
      "name": "Workflow Documentation",
      "type": "n8n-nodes-base.stickyNote",
      "typeVersion": 1,
      "position": [
        100,
        100
      ],
      "parameters": {
        "content": "# Analyze the sentiment of feedback and send a message on Mattermost\n\nAutomated workflow: Analyze the sentiment of feedback and send a message on Mattermost. This workflow processes data and performs automated tasks.\n\n## Nodes:\n- 5 total nodes\n- Includes error handling\n- Follows best practices\n\n## Usage:\n1. Configure credentials\n2. Update environment variables\n3. Test workflow\n4. Deploy to production"
      }
    }
  ],
  "active": false,
  "settings": {
    "executionOrder": "v1",
    "saveManualExecutions": true,
    "callerPolicy": "workflowsFromSameOwner",
    "errorWorkflow": null,
    "timezone": "UTC"
  },
  "connections": {
    "IF": {
      "main": [
        [
          {
            "node": "Mattermost",
            "type": "main",
            "index": 0
          }
        ],
        [
          {
            "node": "NoOp",
            "type": "main",
            "index": 0
          }
        ]
      ]
    },
    "Typeform Trigger": {
      "main": [
        [
          {
            "node": "Google Cloud Natural Language",
            "type": "main",
            "index": 0
          }
        ]
      ]
    },
    "Google Cloud Natural Language": {
      "main": [
        [
          {
            "node": "IF",
            "type": "main",
            "index": 0
          }
        ]
      ]
    }
  },
  "description": "Automated workflow: Analyze the sentiment of feedback and send a message on Mattermost. This workflow processes data and performs automated tasks."
}